{"files":[
{"name":"Compound interest calculator","location":"./Compound-interest-calculator/"},
{"name":"Generating a HTML folder index","location":"./Generating-a-HTML-folder-index/"},
{"name":"TLE dataset format","location":"./TLE-dataset-format/"},
{"name":"Web boilerplate","location":"./Web-boilerplate/"},
{"name":"crypto","location":"./crypto/"},
{"name":"drednot","location":"./drednot/"},
{"name":"exdroid","location":"./exdroid/"},
{"name":"filecan","location":"./filecan/"},
{"name":"isuseless","location":"./isuseless/"}]}
